{
  "project_info": {
    "project_number": "986296058863",
    "project_id": "formation-stage-ete-918b4",
    "storage_bucket": "formation-stage-ete-918b4.appspot.com"
  },
  "client": [
    {
      "client_info": {
        "mobilesdk_app_id": "1:986296058863:android:07b976caaa8f4a7b672c1a",
        "android_client_info": {
          "package_name": "com.example.formationgroupe8"
        }
      },
      "oauth_client": [],
      "api_key": [
        {
          "current_key": "AIzaSyCj2BLloJ-XUQm92aXqiE1s_MKN689QviE"
        }
      ],
      "services": {
        "appinvite_service": {
          "other_platform_oauth_client": []
        }
      }
    }
  ],
  "configuration_version": "1"
}